{"cameraMode":{"drawMode":0,"name":"Shaded","section":"Shading Mode"},"sceneLighting":true,"audioPlay":false,"sceneViewState":{"showFog":true,"showMaterialUpdate":false,"showSkybox":true,"showFlares":true,"showImageEffects":true,"showParticleSystems":true},"in2DMode":false,"pivot":{"x":3.9308576583862306,"y":1.4331440925598145,"z":-3.0665693283081056},"rotation":{"x":-0.09792248159646988,"y":0.8739149570465088,"z":-0.1975448578596115,"w":-0.43319717049598696},"size":10.778799057006836,"orthographic":false}